{"vec_file_metadata":[{"filename":"cargo.toml","filedate":"1582603973.747425100s"},{"filename":"src/ackmsgmod.rs","filedate":"1582558261.588995900s"},{"filename":"src/divgridcontainermod.rs","filedate":"1582603811.899009500s"},{"filename":"src/divplayeractionsmod.rs","filedate":"1582600189.819226400s"},{"filename":"src/fetchmod.rs","filedate":"1582558385.620000000s"},{"filename":"src/gamedatamod.rs","filedate":"1582278210.383505500s"},{"filename":"src/htmltemplateimplmod.rs","filedate":"1582603817.799886400s"},{"filename":"src/lib.rs","filedate":"1582600900.480972700s"},{"filename":"src/rootrenderingcomponentmod.rs","filedate":"1582558261.588995900s"},{"filename":"src/routerimplmod.rs","filedate":"1582558370.316000100s"},{"filename":"src/status1stcardmod.rs","filedate":"1582602384.150535200s"},{"filename":"src/status2ndcardmod.rs","filedate":"1582602404.262958100s"},{"filename":"src/statusdrinkmod.rs","filedate":"1582193595.544937400s"},{"filename":"src/statusgamedatainitmod.rs","filedate":"1582558370.316000100s"},{"filename":"src/statusgameovermod.rs","filedate":"1582603823.346597900s"},{"filename":"src/statusjoinedmod.rs","filedate":"1582558261.588995900s"},{"filename":"src/statusreconnectmod.rs","filedate":"1582603828.967295900s"},{"filename":"src/statustaketurnmod.rs","filedate":"1582558261.588995900s"},{"filename":"src/statuswaitingackmsgmod.rs","filedate":"1582603835.003435000s"},{"filename":"src/storagemod.rs","filedate":"1582558261.588995900s"},{"filename":"src/webdatamod.rs","filedate":"1582558114.265000000s"},{"filename":"src/websocketmod.rs","filedate":"1582558261.588995900s"}]}